datamodel/__init__.py
datamodel/agent.py
datamodel/data.py
datamodel/node.py
datamodel/task.py
datamodel/workflow.py
yProv4WFs_Streamflow/__init__.py
yProv4WFs_Streamflow/yprov4wfs_Streamflow.py
yProv4WFs_Streamflow/yprov4wfs_Streamflow_fromdb.py
yProv4WFs_cylc/__init__.py
yProv4WFs_cylc/yprov4wfs_Cylc.py
yprov4wfs-0.1.0.dist-info/LICENSE
yprov4wfs-0.1.0.dist-info/METADATA
yprov4wfs-0.1.0.dist-info/WHEEL
yprov4wfs-0.1.0.dist-info/top_level.txt
yprov4wfs-0.1.0.dist-info/RECORD
