Metadata-Version: 2.1
Name: yprov4wfs
Version: 0.1.0
Summary: A module for tracking the provenance of a workflow using a Workflow Management System.
Home-page: https://github.com/HPCI-Lab/yProv4WFs
Author: Carolina Sopranzetti
Maintainer: HPCI Lab - University of Trento
License: GNU General Public License v3 (GPLv3)
Classifier: Programming Language :: Python :: 3
Classifier: License :: OSI Approved :: GNU General Public License v3 (GPLv3)
Classifier: Operating System :: OS Independent
Requires-Python: >=3.6
License-File: LICENSE
